kinaid/__init__.py
kinaid/matching.py
kinaid/ortholog.py
kinaid/session.py
kinaid/utility.py
kinaid-1.1.4.dist-info/licenses/LICENSE
kinaid-1.1.4.dist-info/METADATA
kinaid-1.1.4.dist-info/WHEEL
kinaid-1.1.4.dist-info/entry_points.txt
kinaid-1.1.4.dist-info/top_level.txt
kinaid-1.1.4.dist-info/RECORD
