Metadata-Version: 2.4
Name: kinaid
Version: 1.1.4
Summary: KINAID : Kinase Activity and Inference Dashboard
Author-email: "Javed M. Aman" <javeda@princeton.edu>, Mona Singh <mona@cs.princeton.edu>
License: MIT License
Project-URL: homepage, https://kinaid.princeton.edu
Project-URL: repository, https://github.com/Singh-Lab/kinaid
Requires-Python: >=3.10
License-File: LICENSE
Requires-Dist: biopython==1.79
Requires-Dist: numpy
Requires-Dist: scipy
Requires-Dist: scikit-learn
Requires-Dist: pandas
Requires-Dist: tqdm
Requires-Dist: plotly
Requires-Dist: statsmodels
Requires-Dist: dash
Requires-Dist: dash_cytoscape
Requires-Dist: mpire
Requires-Dist: python-calamine
Requires-Dist: xlsxwriter
Requires-Dist: openpyxl
Requires-Dist: pyxlsb
Dynamic: license-file
